gff3_parser/__init__.py
gff3_parser/parser.py
gff3_parser-0.0.5.dist-info/LICENSE
gff3_parser-0.0.5.dist-info/METADATA
gff3_parser-0.0.5.dist-info/WHEEL
gff3_parser-0.0.5.dist-info/top_level.txt
gff3_parser-0.0.5.dist-info/RECORD
