Metadata-Version: 2.1
Name: gff3_parser
Version: 0.0.5
Summary: A package for parsing gff3 (general feature format) files into pandas  dataframes
Home-page: https://github.com/McClain-Thiel/gff3_parser
Author: McClain Thiel
Author-email: mcclain.thiel@gmail.com
License: UNKNOWN
Project-URL: Bug Tracker, https://github.com/pypa/sampleproject/issues
Platform: UNKNOWN
Classifier: Programming Language :: Python :: 3
Classifier: License :: OSI Approved :: MIT License
Classifier: Operating System :: OS Independent
Requires-Python: >=3.6
License-File: LICENSE
